MANIFEST.in
README.md
setup.py
profiler_online/__init__.py
profiler_online/log.py
profiler_online/run.py
profiler_online.egg-info/PKG-INFO
profiler_online.egg-info/SOURCES.txt
profiler_online.egg-info/dependency_links.txt
profiler_online.egg-info/requires.txt
profiler_online.egg-info/top_level.txt
profiler_online/tools/difffolded.pl
profiler_online/tools/flamegraph.pl